webinspectra/__init__.py
webinspectra/__main__.py
webinspectra/inspectra.py
webinspectra/webpage.py
webinspectra/utils/__init__.py
webinspectra/utils/selenium_utils.py
webinspectra/utils/signature_utils.py
WebInspectra-1.0.2.dist-info/LICENSE
WebInspectra-1.0.2.dist-info/METADATA
WebInspectra-1.0.2.dist-info/WHEEL
WebInspectra-1.0.2.dist-info/top_level.txt
WebInspectra-1.0.2.dist-info/RECORD
