Metadata-Version: 2.1
Name: WebInspectra
Version: 1.0.2
Summary: WebInspectra is a Python package designed for detecting web technologies used by a given URL. It provides a method to analyze the technologies powering a website, including frameworks, libraries, CDN usage, advertising platforms, and more. By using various detection patterns and algorithms, WebInspectra identifies and categorizes the technologies utilized in the frontend and backend of web applications.
Home-page: https://github.com/insafm/WebInspectra
Author: Mohammed Insaf M (insafm)
License: GPLv3
Classifier: Development Status :: 3 - Alpha
Classifier: Intended Audience :: Developers
Classifier: Intended Audience :: Information Technology
Classifier: License :: OSI Approved :: GNU General Public License v3 (GPLv3)
Classifier: Programming Language :: Python :: 3
Classifier: Topic :: Internet :: WWW/HTTP
Classifier: Topic :: Security
Requires-Python: >=3.6
License-File: LICENSE
Requires-Dist: beautifulsoup4
Requires-Dist: lxml
Requires-Dist: requests
Requires-Dist: selenium
Requires-Dist: undetected-chromedriver
Requires-Dist: dnspython
Provides-Extra: dev
Requires-Dist: pytest ; extra == 'dev'
Provides-Extra: logging
Requires-Dist: logging ; extra == 'logging'
